[
    {
        "channel_id": "UCager4c99nqQAmdiB7WMZhQ",
        "video_id": "9n0vagkjfGs",
        "video_link": "https://www.youtube.com/watch?v=9n0vagkjfGs",
        "start": 498.3979,
        "end": 498.83166666666665
    },
    {
        "channel_id": "UCager4c99nqQAmdiB7WMZhQ",
        "video_id": "9n0vagkjfGs",
        "video_link": "https://www.youtube.com/watch?v=9n0vagkjfGs",
        "start": 498.8984,
        "end": 500.73356666666666
    },
    {
        "channel_id": "UCager4c99nqQAmdiB7WMZhQ",
        "video_id": "9n0vagkjfGs",
        "video_link": "https://www.youtube.com/watch?v=9n0vagkjfGs",
        "start": 517.4836333333334,
        "end": 523.1893333333334
    }
]