[
    {
        "channel_id": "UCager4c99nqQAmdiB7WMZhQ",
        "video_id": "Iv09oJc_cMc",
        "video_link": "https://www.youtube.com/watch?v=Iv09oJc_cMc",
        "start": 688.7297083333333,
        "end": 689.689
    },
    {
        "channel_id": "UCager4c99nqQAmdiB7WMZhQ",
        "video_id": "Iv09oJc_cMc",
        "video_link": "https://www.youtube.com/watch?v=Iv09oJc_cMc",
        "start": 800.6331666666666,
        "end": 801.7175833333333
    },
    {
        "channel_id": "UCager4c99nqQAmdiB7WMZhQ",
        "video_id": "Iv09oJc_cMc",
        "video_link": "https://www.youtube.com/watch?v=Iv09oJc_cMc",
        "start": 879.5870416666666,
        "end": 880.62975
    },
    {
        "channel_id": "UCager4c99nqQAmdiB7WMZhQ",
        "video_id": "Iv09oJc_cMc",
        "video_link": "https://www.youtube.com/watch?v=Iv09oJc_cMc",
        "start": 900.1909583333332,
        "end": 902.9854166666667
    },
    {
        "channel_id": "UCager4c99nqQAmdiB7WMZhQ",
        "video_id": "Iv09oJc_cMc",
        "video_link": "https://www.youtube.com/watch?v=Iv09oJc_cMc",
        "start": 929.2199583333332,
        "end": 929.929
    },
    {
        "channel_id": "UCager4c99nqQAmdiB7WMZhQ",
        "video_id": "Iv09oJc_cMc",
        "video_link": "https://www.youtube.com/watch?v=Iv09oJc_cMc",
        "start": 949.949,
        "end": 951.3253749999999
    },
    {
        "channel_id": "UCager4c99nqQAmdiB7WMZhQ",
        "video_id": "Iv09oJc_cMc",
        "video_link": "https://www.youtube.com/watch?v=Iv09oJc_cMc",
        "start": 951.6590416666666,
        "end": 952.1595416666667
    }
]