[
    {
        "channel_id": "UCager4c99nqQAmdiB7WMZhQ",
        "video_id": "JDkAf5uGFp8",
        "video_link": "https://www.youtube.com/watch?v=JDkAf5uGFp8",
        "start": 587.0531333333333,
        "end": 587.7204666666667
    },
    {
        "channel_id": "UCager4c99nqQAmdiB7WMZhQ",
        "video_id": "JDkAf5uGFp8",
        "video_link": "https://www.youtube.com/watch?v=JDkAf5uGFp8",
        "start": 706.7393666666667,
        "end": 707.707
    },
    {
        "channel_id": "UCager4c99nqQAmdiB7WMZhQ",
        "video_id": "JDkAf5uGFp8",
        "video_link": "https://www.youtube.com/watch?v=JDkAf5uGFp8",
        "start": 709.2418666666666,
        "end": 710.3763333333334
    },
    {
        "channel_id": "UCager4c99nqQAmdiB7WMZhQ",
        "video_id": "JDkAf5uGFp8",
        "video_link": "https://www.youtube.com/watch?v=JDkAf5uGFp8",
        "start": 727.5601666666666,
        "end": 730.3963333333334
    },
    {
        "channel_id": "UCager4c99nqQAmdiB7WMZhQ",
        "video_id": "JDkAf5uGFp8",
        "video_link": "https://www.youtube.com/watch?v=JDkAf5uGFp8",
        "start": 758.8581,
        "end": 759.6922666666667
    }
]