[
    {
        "channel_id": "UCu7DiFkpfeNUGIQNs_czJXg",
        "video_id": "LZ1RYEdthJ4",
        "video_link": "https://www.youtube.com/watch?v=LZ1RYEdthJ4",
        "start": 118.95216666666667,
        "end": 120.3202
    },
    {
        "channel_id": "UCu7DiFkpfeNUGIQNs_czJXg",
        "video_id": "LZ1RYEdthJ4",
        "video_link": "https://www.youtube.com/watch?v=LZ1RYEdthJ4",
        "start": 170.40356666666668,
        "end": 171.6715
    },
    {
        "channel_id": "UCu7DiFkpfeNUGIQNs_czJXg",
        "video_id": "LZ1RYEdthJ4",
        "video_link": "https://www.youtube.com/watch?v=LZ1RYEdthJ4",
        "start": 178.94543333333334,
        "end": 181.04753333333335
    },
    {
        "channel_id": "UCu7DiFkpfeNUGIQNs_czJXg",
        "video_id": "LZ1RYEdthJ4",
        "video_link": "https://www.youtube.com/watch?v=LZ1RYEdthJ4",
        "start": 191.52466666666666,
        "end": 192.25873333333334
    },
    {
        "channel_id": "UCu7DiFkpfeNUGIQNs_czJXg",
        "video_id": "LZ1RYEdthJ4",
        "video_link": "https://www.youtube.com/watch?v=LZ1RYEdthJ4",
        "start": 209.1089,
        "end": 209.62608333333333
    },
    {
        "channel_id": "UCu7DiFkpfeNUGIQNs_czJXg",
        "video_id": "LZ1RYEdthJ4",
        "video_link": "https://www.youtube.com/watch?v=LZ1RYEdthJ4",
        "start": 209.64276666666666,
        "end": 210.1099
    },
    {
        "channel_id": "UCu7DiFkpfeNUGIQNs_czJXg",
        "video_id": "LZ1RYEdthJ4",
        "video_link": "https://www.youtube.com/watch?v=LZ1RYEdthJ4",
        "start": 210.7105,
        "end": 211.24436666666668
    },
    {
        "channel_id": "UCu7DiFkpfeNUGIQNs_czJXg",
        "video_id": "LZ1RYEdthJ4",
        "video_link": "https://www.youtube.com/watch?v=LZ1RYEdthJ4",
        "start": 217.18363333333335,
        "end": 217.7175
    },
    {
        "channel_id": "UCu7DiFkpfeNUGIQNs_czJXg",
        "video_id": "LZ1RYEdthJ4",
        "video_link": "https://www.youtube.com/watch?v=LZ1RYEdthJ4",
        "start": 218.35146666666668,
        "end": 219.51930000000002
    },
    {
        "channel_id": "UCu7DiFkpfeNUGIQNs_czJXg",
        "video_id": "LZ1RYEdthJ4",
        "video_link": "https://www.youtube.com/watch?v=LZ1RYEdthJ4",
        "start": 221.5213,
        "end": 222.0218
    },
    {
        "channel_id": "UCu7DiFkpfeNUGIQNs_czJXg",
        "video_id": "LZ1RYEdthJ4",
        "video_link": "https://www.youtube.com/watch?v=LZ1RYEdthJ4",
        "start": 226.0258,
        "end": 227.227
    },
    {
        "channel_id": "UCu7DiFkpfeNUGIQNs_czJXg",
        "video_id": "LZ1RYEdthJ4",
        "video_link": "https://www.youtube.com/watch?v=LZ1RYEdthJ4",
        "start": 236.50293333333335,
        "end": 237.0368
    },
    {
        "channel_id": "UCu7DiFkpfeNUGIQNs_czJXg",
        "video_id": "LZ1RYEdthJ4",
        "video_link": "https://www.youtube.com/watch?v=LZ1RYEdthJ4",
        "start": 242.242,
        "end": 245.47856666666667
    },
    {
        "channel_id": "UCu7DiFkpfeNUGIQNs_czJXg",
        "video_id": "LZ1RYEdthJ4",
        "video_link": "https://www.youtube.com/watch?v=LZ1RYEdthJ4",
        "start": 250.81723333333335,
        "end": 251.68476666666666
    },
    {
        "channel_id": "UCu7DiFkpfeNUGIQNs_czJXg",
        "video_id": "LZ1RYEdthJ4",
        "video_link": "https://www.youtube.com/watch?v=LZ1RYEdthJ4",
        "start": 255.92233333333334,
        "end": 256.72313333333335
    },
    {
        "channel_id": "UCu7DiFkpfeNUGIQNs_czJXg",
        "video_id": "LZ1RYEdthJ4",
        "video_link": "https://www.youtube.com/watch?v=LZ1RYEdthJ4",
        "start": 310.27663333333334,
        "end": 310.74376666666666
    },
    {
        "channel_id": "UCu7DiFkpfeNUGIQNs_czJXg",
        "video_id": "LZ1RYEdthJ4",
        "video_link": "https://www.youtube.com/watch?v=LZ1RYEdthJ4",
        "start": 369.16880000000003,
        "end": 370.2699
    },
    {
        "channel_id": "UCu7DiFkpfeNUGIQNs_czJXg",
        "video_id": "LZ1RYEdthJ4",
        "video_link": "https://www.youtube.com/watch?v=LZ1RYEdthJ4",
        "start": 387.2869,
        "end": 388.1878
    }
]